spidercreator/__init__.py
spidercreator-0.0.1.dist-info/licenses/LICENSE.md
spidercreator-0.0.1.dist-info/METADATA
spidercreator-0.0.1.dist-info/WHEEL
spidercreator-0.0.1.dist-info/top_level.txt
spidercreator-0.0.1.dist-info/RECORD
